Metadata-Version: 2.0
Name: zerorpc-2
Version: 0.7.0
Summary: zerorpc is a flexible RPC based on zeromq. With Numpy Support
Home-page: https://github.com/MichaelScript/zerorpc-python
Author: François-Xavier Bourlet <bombela+zerorpc@gmail.com>.
Author-email: UNKNOWN
License: MIT
Platform: UNKNOWN
Classifier: Development Status :: 5 - Production/Stable
Classifier: Intended Audience :: Developers
Classifier: Natural Language :: English
Classifier: License :: OSI Approved :: MIT License
Classifier: Programming Language :: Python
Classifier: Programming Language :: Python :: 2.6
Classifier: Programming Language :: Python :: 2.7
Classifier: Programming Language :: Python :: 3.4
Requires-Dist: msgpack (>=0.5.2)
Requires-Dist: pyzmq (>=13.1.0)
Requires-Dist: msgpack-numpy (>=0.4.3)
Requires-Dist: future
Requires-Dist: gevent (>=1.1rc5)
